COPYING
COPYING.LESSER
MANIFEST.in
README.md
setup.py
github/AuthenticatedUser.py
github/Authorization.py
github/AuthorizationApplication.py
github/Branch.py
github/Commit.py
github/CommitCombinedStatus.py
github/CommitComment.py
github/CommitStats.py
github/CommitStatus.py
github/Comparison.py
github/Consts.py
github/ContentFile.py
github/Download.py
github/Event.py
github/File.py
github/Gist.py
github/GistComment.py
github/GistFile.py
github/GistHistoryState.py
github/GitAuthor.py
github/GitBlob.py
github/GitCommit.py
github/GitObject.py
github/GitRef.py
github/GitRelease.py
github/GitTag.py
github/GitTree.py
github/GitTreeElement.py
github/GithubException.py
github/GithubObject.py
github/GitignoreTemplate.py
github/Hook.py
github/HookDescription.py
github/HookResponse.py
github/InputFileContent.py
github/InputGitAuthor.py
github/InputGitTreeElement.py
github/Issue.py
github/IssueComment.py
github/IssueEvent.py
github/IssuePullRequest.py
github/Label.py
github/Legacy.py
github/MainClass.py
github/Milestone.py
github/NamedUser.py
github/Notification.py
github/NotificationSubject.py
github/Organization.py
github/PaginatedList.py
github/Permissions.py
github/Plan.py
github/PullRequest.py
github/PullRequestComment.py
github/PullRequestMergeStatus.py
github/PullRequestPart.py
github/Rate.py
github/RateLimit.py
github/Repository.py
github/RepositoryKey.py
github/Requester.py
github/Stargazer.py
github/StatsCodeFrequency.py
github/StatsCommitActivity.py
github/StatsContributor.py
github/StatsParticipation.py
github/StatsPunchCard.py
github/Status.py
github/StatusMessage.py
github/Tag.py
github/Team.py
github/UserKey.py
github/__init__.py
github/tests/AllTests.py
github/tests/AuthenticatedUser.py
github/tests/Authentication.py
github/tests/Authorization.py
github/tests/BadAttributes.py
github/tests/Branch.py
github/tests/Commit.py
github/tests/CommitCombinedStatus.py
github/tests/CommitComment.py
github/tests/CommitStatus.py
github/tests/ConditionalRequestUpdate.py
pygithub_redux.egg-info/PKG-INFO
pygithub_redux.egg-info/SOURCES.txt
pygithub_redux.egg-info/dependency_links.txt
pygithub_redux.egg-info/top_level.txt